changelog_maestro/__init__.py
changelog_maestro/__main__.py
changelog_maestro/cli.py
changelog_maestro/py.typed
changelog_maestro/core/__init__.py
changelog_maestro/core/config.py
changelog_maestro/core/formatter.py
changelog_maestro/core/generator.py
changelog_maestro/core/git.py
changelog_maestro/core/parser.py
changelog_maestro/templates/__init__.py
changelog_maestro/templates/default.md.j2
changelog_maestro/utils/__init__.py
changelog_maestro/utils/exceptions.py
git_changelog_maestro-0.1.2.dist-info/METADATA
git_changelog_maestro-0.1.2.dist-info/WHEEL
git_changelog_maestro-0.1.2.dist-info/entry_points.txt
git_changelog_maestro-0.1.2.dist-info/licenses/LICENSE
git_changelog_maestro-0.1.2.dist-info/RECORD
