Metadata-Version: 2.4
Name: git-changelog-maestro
Version: 0.1.2
Summary: Generate elegant changelogs from Git commit history using Conventional Commits
Project-URL: Homepage, https://github.com/petherldev/git-changelog-maestro
Project-URL: Repository, https://github.com/petherldev/git-changelog-maestro
Project-URL: Issues, https://github.com/petherldev/git-changelog-maestro/issues
Project-URL: Changelog, https://github.com/petherldev/git-changelog-maestro/blob/main/CHANGELOG.md
Author-email: petherldev <petherl@protonmail.com>
License-Expression: MIT
License-File: LICENSE
Keywords: changelog,cli,conventional-commits,git,semantic-versioning
Classifier: Development Status :: 5 - Production/Stable
Classifier: Environment :: Console
Classifier: Intended Audience :: Developers
Classifier: License :: OSI Approved :: MIT License
Classifier: Operating System :: OS Independent
Classifier: Programming Language :: Python :: 3.11
Classifier: Programming Language :: Python :: 3.12
Classifier: Topic :: Software Development :: Documentation
Classifier: Topic :: Software Development :: Version Control :: Git
Classifier: Topic :: Utilities
Requires-Python: >=3.11
Requires-Dist: click>=8.0.0
Requires-Dist: gitpython>=3.1.0
Requires-Dist: jinja2>=3.0.0
Requires-Dist: pydantic>=2.0.0
Requires-Dist: pyyaml>=6.0.0
Requires-Dist: rich>=13.0.0
Requires-Dist: tomli>=2.0.0; python_version < '3.11'
Provides-Extra: dev
Requires-Dist: black>=23.0.0; extra == 'dev'
Requires-Dist: flake8>=6.0.0; extra == 'dev'
Requires-Dist: isort>=5.12.0; extra == 'dev'
Requires-Dist: mypy>=1.0.0; extra == 'dev'
Requires-Dist: pre-commit>=3.0.0; extra == 'dev'
Requires-Dist: pytest-cov>=4.0.0; extra == 'dev'
Requires-Dist: pytest-mock>=3.10.0; extra == 'dev'
Requires-Dist: pytest>=7.0.0; extra == 'dev'
Requires-Dist: types-pyyaml; extra == 'dev'
